collepedia/__init__.py
collepedia/client.py
collepedia/exceptions.py
collepedia-1.1.0.dist-info/METADATA
collepedia-1.1.0.dist-info/WHEEL
collepedia-1.1.0.dist-info/top_level.txt
collepedia-1.1.0.dist-info/RECORD
