Metadata-Version: 2.4
Name: collepedia
Version: 1.1.0
Summary: A dedicated client to fetch and manage posts from Collepedia.
Author-email: AbdulRahman Muhammad Rabie Ahmed <bedob3401@gmail.com>, Nanosoft Technologies Agency <nanosofttechcom@gmail.com>
Project-URL: Homepage, https://colle-pedia.blogspot.com/?fwd=collepediapy
Classifier: Programming Language :: Python :: 3
Classifier: License :: OSI Approved :: MIT License
Classifier: Operating System :: OS Independent
Classifier: Topic :: Software Development :: Libraries :: Python Modules
Requires-Python: >=3.8
Requires-Dist: requests>=2.28.0
Requires-Dist: feedparser>=6.0.0
